dev/benchmarks/bench_import_open.py
dev/scripts/find_missing_fixtures.py
dev/scripts/inspect_zip.py
dev/scripts/verify_output.py
docs/node_modules/shell-quote/print.py
examples/converter/convert.py
examples/simplewiki/convert.py
examples/simplewiki/convert_parquet.py
examples/simplewiki/enrich.py
examples/zipxml/process_rmsp_zip.py
iterable/__init__.py
iterable/base.py
iterable/exceptions.py
iterable/py.typed
iterable/types.py
iterable/codecs/__init__.py
iterable/codecs/brotlicodec.py
iterable/codecs/bz2codec.py
iterable/codecs/gzipcodec.py
iterable/codecs/lz4codec.py
iterable/codecs/lzmacodec.py
iterable/codecs/lzocodec.py
iterable/codecs/rawcodec.py
iterable/codecs/snappycodec.py
iterable/codecs/szipcodec.py
iterable/codecs/zipcodec.py
iterable/codecs/zstdcodec.py
iterable/convert/__init__.py
iterable/convert/core.py
iterable/datatypes/__init__.py
iterable/datatypes/annotatedcsv.py
iterable/datatypes/apachelog.py
iterable/datatypes/arff.py
iterable/datatypes/arrow.py
iterable/datatypes/asn1.py
iterable/datatypes/avro.py
iterable/datatypes/beam.py
iterable/datatypes/bencode.py
iterable/datatypes/bsonf.py
iterable/datatypes/capnp.py
iterable/datatypes/cbor.py
iterable/datatypes/cdx.py
iterable/datatypes/cef.py
iterable/datatypes/csv.py
iterable/datatypes/csvw.py
iterable/datatypes/dbf.py
iterable/datatypes/delta.py
iterable/datatypes/duckdb.py
iterable/datatypes/dxf.py
iterable/datatypes/edn.py
iterable/datatypes/eml.py
iterable/datatypes/feed.py
iterable/datatypes/flatbuffers.py
iterable/datatypes/flexbuffers.py
iterable/datatypes/flink.py
iterable/datatypes/fwf.py
iterable/datatypes/gelf.py
iterable/datatypes/geojson.py
iterable/datatypes/geopackage.py
iterable/datatypes/gml.py
iterable/datatypes/hdf5.py
iterable/datatypes/hocon.py
iterable/datatypes/html.py
iterable/datatypes/hudi.py
iterable/datatypes/ical.py
iterable/datatypes/iceberg.py
iterable/datatypes/ilp.py
iterable/datatypes/ini.py
iterable/datatypes/ion.py
iterable/datatypes/json.py
iterabledata-1.0.11.dist-info/licenses/LICENSE
iterabledata-1.0.11.dist-info/METADATA
iterabledata-1.0.11.dist-info/WHEEL
iterabledata-1.0.11.dist-info/top_level.txt
iterabledata-1.0.11.dist-info/RECORD
