Metadata-Version: 2.4
Name: iterabledata
Version: 1.0.11
Summary: Iterable data processing Python library
Author: Ivan Begtin
License: MIT
Project-URL: Homepage, https://github.com/datenoio/iterabledata/
Project-URL: Repository, https://github.com/datenoio/iterabledata/
Keywords: json,jsonl,csv,bson,parquet,orc,xml,xls,xlsx,dbf,dataset,etl,data-pipelines
Classifier: Development Status :: 5 - Production/Stable
Classifier: Programming Language :: Python
Classifier: Programming Language :: Python :: 3 :: Only
Classifier: Programming Language :: Python :: 3.10
Classifier: Programming Language :: Python :: 3.11
Classifier: Programming Language :: Python :: 3.12
Classifier: Environment :: Console
Classifier: Intended Audience :: Developers
Classifier: Intended Audience :: System Administrators
Classifier: License :: OSI Approved :: MIT License
Classifier: Topic :: Software Development
Classifier: Topic :: Text Processing
Requires-Python: >=3.10
License-File: LICENSE
Requires-Dist: chardet>=5.0.0
Requires-Dist: tqdm>=4.64.0
Provides-Extra: compression
Requires-Dist: lz4>=4.0.0; extra == "compression"
Requires-Dist: python-snappy>=0.6.0; extra == "compression"
Requires-Dist: python-lzo>=1.12.0; extra == "compression"
Requires-Dist: brotli>=1.0.0; extra == "compression"
Requires-Dist: brotli_file>=1.0.0; extra == "compression"
Requires-Dist: zstandard>=0.19.0; extra == "compression"
Provides-Extra: parquet
Requires-Dist: pyarrow>=10.0.0; extra == "parquet"
Provides-Extra: orc
Requires-Dist: pyorc>=1.6.0; extra == "orc"
Provides-Extra: excel
Requires-Dist: xlrd>=2.0.0; extra == "excel"
Requires-Dist: openpyxl>=3.0.0; extra == "excel"
Provides-Extra: xml
Requires-Dist: lxml>=4.9.0; extra == "xml"
Provides-Extra: bson
Requires-Dist: pymongo>=4.0.0; extra == "bson"
Provides-Extra: dbf
Requires-Dist: dbfread>=2.0.0; extra == "dbf"
Provides-Extra: warc
Requires-Dist: warcio>=1.7.0; extra == "warc"
Provides-Extra: duckdb
Requires-Dist: duckdb>=0.9.0; extra == "duckdb"
Provides-Extra: stats
Requires-Dist: pyreadstat>=1.2.0; extra == "stats"
Provides-Extra: protobuf
Requires-Dist: protobuf>=4.0.0; extra == "protobuf"
Provides-Extra: ion
Requires-Dist: ion-python>=1.0.0; extra == "ion"
Provides-Extra: hdf5
Requires-Dist: h5py>=3.0.0; extra == "hdf5"
Provides-Extra: geospatial
Requires-Dist: geojson>=3.0.0; extra == "geospatial"
Requires-Dist: pyshp>=2.3.0; extra == "geospatial"
Requires-Dist: fiona>=1.9.0; extra == "geospatial"
Requires-Dist: mapbox-vector-tile>=1.2.0; extra == "geospatial"
Requires-Dist: topojson>=1.5.0; extra == "geospatial"
Provides-Extra: toml
Requires-Dist: tomli>=2.0.0; extra == "toml"
Requires-Dist: tomli-w>=1.0.0; extra == "toml"
Requires-Dist: toml>=0.10.0; extra == "toml"
Provides-Extra: msgpack
Requires-Dist: msgpack>=1.0.0; extra == "msgpack"
Provides-Extra: yaml
Requires-Dist: pyyaml>=6.0.0; extra == "yaml"
Provides-Extra: pcap
Requires-Dist: dpkt>=1.9.0; extra == "pcap"
Provides-Extra: netcdf
Requires-Dist: netCDF4>=1.6.0; extra == "netcdf"
Provides-Extra: mvt
Requires-Dist: mapbox-vector-tile>=1.2.0; extra == "mvt"
Provides-Extra: topojson
Requires-Dist: topojson>=1.5.0; extra == "topojson"
Provides-Extra: feed
Requires-Dist: feedparser>=6.0.0; extra == "feed"
Provides-Extra: dxf
Requires-Dist: ezdxf>=1.0.0; extra == "dxf"
Provides-Extra: html
Requires-Dist: beautifulsoup4>=4.11.0; extra == "html"
Provides-Extra: arff
Requires-Dist: liac-arff>=2.5.0; extra == "arff"
Provides-Extra: json
Requires-Dist: ijson>=3.2.0; extra == "json"
Provides-Extra: vortex
Requires-Dist: vortex-data>=0.56.0; extra == "vortex"
Provides-Extra: pydantic
Requires-Dist: pydantic>=2.0.0; extra == "pydantic"
Provides-Extra: dataframes
Requires-Dist: pandas>=1.5.0; extra == "dataframes"
Requires-Dist: polars>=0.19.0; extra == "dataframes"
Requires-Dist: dask[dataframe]>=2023.1.0; extra == "dataframes"
Provides-Extra: cloud
Requires-Dist: fsspec>=2023.1.0; extra == "cloud"
Requires-Dist: s3fs>=2023.1.0; extra == "cloud"
Requires-Dist: gcsfs>=2023.1.0; extra == "cloud"
Requires-Dist: adlfs>=2023.1.0; extra == "cloud"
Provides-Extra: all
Requires-Dist: lz4>=4.0.0; extra == "all"
Requires-Dist: python-snappy>=0.6.0; extra == "all"
Requires-Dist: python-lzo>=1.12.0; extra == "all"
Requires-Dist: brotli>=1.0.0; extra == "all"
Requires-Dist: brotli_file>=1.0.0; extra == "all"
Requires-Dist: zstandard>=0.19.0; extra == "all"
Requires-Dist: pyarrow>=10.0.0; extra == "all"
Requires-Dist: pyorc>=1.6.0; extra == "all"
Requires-Dist: xlrd>=2.0.0; extra == "all"
Requires-Dist: openpyxl>=3.0.0; extra == "all"
Requires-Dist: lxml>=4.9.0; extra == "all"
Requires-Dist: pymongo>=4.0.0; extra == "all"
Requires-Dist: dbfread>=2.0.0; extra == "all"
Requires-Dist: warcio>=1.7.0; extra == "all"
Requires-Dist: duckdb>=0.9.0; extra == "all"
Requires-Dist: pyreadstat>=1.2.0; extra == "all"
Requires-Dist: protobuf>=4.0.0; extra == "all"
Requires-Dist: ion-python>=1.0.0; extra == "all"
Requires-Dist: h5py>=3.0.0; extra == "all"
Requires-Dist: geojson>=3.0.0; extra == "all"
Requires-Dist: pyshp>=2.3.0; extra == "all"
Requires-Dist: fiona>=1.9.0; extra == "all"
Requires-Dist: tomli>=2.0.0; extra == "all"
Requires-Dist: tomli-w>=1.0.0; extra == "all"
Requires-Dist: toml>=0.10.0; extra == "all"
Requires-Dist: msgpack>=1.0.0; extra == "all"
Requires-Dist: pyyaml>=6.0.0; extra == "all"
Requires-Dist: dpkt>=1.9.0; extra == "all"
Requires-Dist: netCDF4>=1.6.0; extra == "all"
Requires-Dist: mapbox-vector-tile>=1.2.0; extra == "all"
Requires-Dist: topojson>=1.5.0; extra == "all"
Requires-Dist: feedparser>=6.0.0; extra == "all"
Requires-Dist: ezdxf>=1.0.0; extra == "all"
Requires-Dist: beautifulsoup4>=4.11.0; extra == "all"
Requires-Dist: liac-arff>=2.5.0; extra == "all"
Requires-Dist: ijson>=3.2.0; extra == "all"
Requires-Dist: vortex-data>=0.56.0; extra == "all"
Requires-Dist: pydantic>=2.0.0; extra == "all"
Requires-Dist: pandas>=1.5.0; extra == "all"
Requires-Dist: polars>=0.19.0; extra == "all"
Requires-Dist: dask[dataframe]>=2023.1.0; extra == "all"
Requires-Dist: fsspec>=2023.1.0; extra == "all"
Requires-Dist: s3fs>=2023.1.0; extra == "all"
Requires-Dist: gcsfs>=2023.1.0; extra == "all"
Requires-Dist: adlfs>=2023.1.0; extra == "all"
Provides-Extra: dev
Requires-Dist: pytest>=7.0.0; extra == "dev"
Requires-Dist: pytest-benchmark>=4.0.0; extra == "dev"
Requires-Dist: pytest-cov>=4.1.0; extra == "dev"
Requires-Dist: pytest-xdist>=3.3.0; extra == "dev"
Requires-Dist: pytest-timeout>=2.2.0; extra == "dev"
Requires-Dist: mock>=4.0.0; extra == "dev"
Requires-Dist: ruff>=0.1.0; extra == "dev"
Requires-Dist: mypy>=1.0.0; extra == "dev"
Requires-Dist: types-chardet>=5.0.0; extra == "dev"
Requires-Dist: types-openpyxl>=3.0.0; extra == "dev"
Requires-Dist: hypothesis>=6.0.0; extra == "dev"
Requires-Dist: pandas>=1.5.0; extra == "dev"
Requires-Dist: bandit[toml]>=1.7.5; extra == "dev"
Requires-Dist: pip-audit>=2.6.1; extra == "dev"
Requires-Dist: safety>=2.3.0; extra == "dev"
Requires-Dist: vulture>=2.10; extra == "dev"
Requires-Dist: radon>=6.0.0; extra == "dev"
Requires-Dist: pydocstyle[toml]>=6.3.0; extra == "dev"
Requires-Dist: coverage[toml]>=7.3.0; extra == "dev"
Requires-Dist: pip-tools>=7.3.0; extra == "dev"
Requires-Dist: pipdeptree>=2.9.0; extra == "dev"
Requires-Dist: pip-licenses>=4.3.0; extra == "dev"
Requires-Dist: build>=1.0.0; extra == "dev"
Requires-Dist: twine>=4.0.0; extra == "dev"
Requires-Dist: check-wheel-contents>=0.5.0; extra == "dev"
Dynamic: license-file
